<?xml version="1.0" encoding="UTF-8"?>
<item><pubDate>Sun, 26 Jan 2014 19:26:07 -0500</pubDate><title><![CDATA[Shabbat Zachor]]></title><url><![CDATA[shabbat-zachor]]></url><meta><![CDATA[]]></meta><metad><![CDATA[]]></metad><menu><![CDATA[Shabbat Zachor]]></menu><menuOrder><![CDATA[0]]></menuOrder><menuStatus><![CDATA[]]></menuStatus><template><![CDATA[template.php]]></template><parent><![CDATA[]]></parent><content><![CDATA[&lt;h3&gt;Shabbat Zachor&lt;/h3&gt;
&lt;h4&gt;General Notes&lt;/h4&gt;
&lt;p&gt;Shabbat Zachor is the second in a series of five special Shabbatot before Pesach. On Shabbat Zachor, we commemorate the actions of Amalek, who attacked the Israelites after they left Egypt. The traditional Haftarah from I Samuel continues on this theme, recalling a battle between the Israelites and Amalekites during the days of King Saul. In this Haftarah, the king of the Amalekites is identified as Agag. Shabbat Zachor occurs the week before Purim because, in Megillat Esther, Haman is called an Agagite, and is thus considered to be a descendant of Amalek. Some Reform synagogues read a selection from the book of Esther as an alternative to the traditional Haftarah.&lt;/p&gt;
&lt;h4&gt;Shacharit Torah Reading - Scroll #2&lt;/h4&gt;
&lt;p&gt;Deuteronomy 25:17-19 (P 1507, RP 688, WTC 1184)&lt;/p&gt;
&lt;p&gt;1 Aliyah&lt;/p&gt;
&lt;h4&gt;Shacharit Haftarah - Traditional&lt;/h4&gt;
&lt;p&gt;I Samuel 15:2-15:34&lt;/p&gt;
&lt;h4&gt;Shacharit Haftarah - Alternative&lt;/h4&gt;
&lt;p&gt;Esther 7:1-10, 8:15-17 (P 1649, RP 1453)&lt;/p&gt;
]]></content><private><![CDATA[]]></private><author><![CDATA[amanda]]></author></item>
